neuradoc/__init__.py
neuradoc/analyzer.py
neuradoc/config.py
neuradoc/classifiers/__init__.py
neuradoc/classifiers/element_classifier.py
neuradoc/extractors/__init__.py
neuradoc/extractors/diagram_extractor.py
neuradoc/extractors/image_extractor.py
neuradoc/extractors/table_extractor.py
neuradoc/extractors/text_extractor.py
neuradoc/models/__init__.py
neuradoc/models/document.py
neuradoc/models/element.py
neuradoc/parsers/__init__.py
neuradoc/parsers/csv_parser.py
neuradoc/parsers/docx_parser.py
neuradoc/parsers/html_parser.py
neuradoc/parsers/image_parser.py
neuradoc/parsers/json_parser.py
neuradoc/parsers/markdown_parser.py
neuradoc/parsers/pdf_parser.py
neuradoc/parsers/pptx_parser.py
neuradoc/parsers/txt_parser.py
neuradoc/parsers/xlsx_parser.py
neuradoc/parsers/xml_parser.py
neuradoc/transformers/__init__.py
neuradoc/transformers/llm_transformer.py
neuradoc/utils/__init__.py
neuradoc/utils/exceptions.py
neuradoc/utils/ocr.py
neuradoc/utils/validators.py
neuradoc-0.1.2.dist-info/licenses/LICENSE
neuradoc-0.1.2.dist-info/METADATA
neuradoc-0.1.2.dist-info/WHEEL
neuradoc-0.1.2.dist-info/top_level.txt
neuradoc-0.1.2.dist-info/RECORD
