Metadata-Version: 2.4
Name: neuradoc
Version: 0.1.2
Summary: A Python package for parsing and transforming various document formats into LLM-ready data with element classification capabilities
Home-page: https://github.com/neuradoc/neuradoc
Author: NeuraDoc Team
Author-email: NeuraDoc Team <neuradoc@example.com>
Project-URL: Bug Tracker, https://github.com/neuradoc/neuradoc/issues
Project-URL: Documentation, https://github.com/neuradoc/neuradoc
Project-URL: Source Code, https://github.com/neuradoc/neuradoc
Classifier: Development Status :: 3 - Alpha
Classifier: Intended Audience :: Developers
Classifier: Topic :: Software Development :: Libraries :: Python Modules
Classifier: Topic :: Text Processing :: General
Classifier: Programming Language :: Python :: 3
Classifier: Programming Language :: Python :: 3.8
Classifier: Programming Language :: Python :: 3.9
Classifier: Programming Language :: Python :: 3.10
Classifier: Programming Language :: Python :: 3.11
Classifier: License :: OSI Approved :: MIT License
Classifier: Operating System :: OS Independent
Requires-Python: >=3.8
License-File: LICENSE
Requires-Dist: PyPDF2>=2.0.0
Requires-Dist: python-docx>=0.8.11
Requires-Dist: openpyxl>=3.0.10
Requires-Dist: beautifulsoup4>=4.10.0
Requires-Dist: lxml>=4.6.5
Requires-Dist: pillow>=9.0.0
Requires-Dist: numpy>=1.20.0
Requires-Dist: pandas>=1.3.0
Requires-Dist: python-pptx>=0.6.21
Requires-Dist: requests>=2.27.0
Requires-Dist: pyarmor>=9.1.2
Requires-Dist: flask>=3.0.3
Requires-Dist: setuptools>=75.3.2
Requires-Dist: werkzeug>=3.0.6
Requires-Dist: build>=1.2.2.post1
Requires-Dist: twine>=6.1.0
Requires-Dist: trafilatura>=1.6.1
Requires-Dist: gunicorn>=23.0.0
Provides-Extra: ocr
Requires-Dist: pytesseract>=0.3.8; extra == "ocr"
Provides-Extra: tables
Requires-Dist: camelot-py>=0.10.1; extra == "tables"
Requires-Dist: tabula-py>=2.3.0; extra == "tables"
Provides-Extra: nlp
Requires-Dist: spacy>=3.2.0; extra == "nlp"
Provides-Extra: transformers
Requires-Dist: transformers>=4.16.0; extra == "transformers"
Requires-Dist: torch>=1.10.0; extra == "transformers"
Provides-Extra: web
Requires-Dist: flask>=2.0.0; extra == "web"
Requires-Dist: gunicorn>=20.0.0; extra == "web"
Dynamic: author
Dynamic: home-page
Dynamic: license-file
Dynamic: requires-python
